{
  "checksum": {
    "previous": "54808d178b3543d34027c3ed2e1efb1b24ce25ee680360ff94e3dfc9be3499c7",
    "current": "b173d1feb0475b40494c460b514859cb6bf3b4dba95d284990fa890240a02e8c"
  },
  "fonts": [

  ],
  "glyphs": {
    "arrow-back": {
      "source": "svg/arrow-back.svg",
      "codepoint": 61811
    },
    "arrow-down": {
      "source": "svg/arrow-down.svg",
      "codepoint": 61812
    },
    "arrow-down-lean": {
      "source": "svg/arrow-down-lean.svg",
      "codepoint": 61813
    },
    "arrow-left": {
      "source": "svg/arrow-left.svg",
      "codepoint": 61814
    },
    "arrow-left-lean": {
      "source": "svg/arrow-left-lean.svg",
      "codepoint": 61815
    },
    "arrow-next": {
      "source": "svg/arrow-next.svg",
      "codepoint": 61816
    },
    "arrow-right": {
      "source": "svg/arrow-right.svg",
      "codepoint": 61817
    },
    "arrow-right-lean": {
      "source": "svg/arrow-right-lean.svg",
      "codepoint": 61818
    },
    "arrow-up": {
      "source": "svg/arrow-up.svg",
      "codepoint": 61819
    },
    "arrow-up-lean": {
      "source": "svg/arrow-up-lean.svg",
      "codepoint": 61820
    },
    "arrow-up-left": {
      "source": "svg/arrow-up-left.svg",
      "codepoint": 61821
    },
    "audio": {
      "source": "svg/audio.svg",
      "codepoint": 61822
    },
    "bars": {
      "source": "svg/bars.svg",
      "codepoint": 61823
    },
    "bullet": {
      "source": "svg/bullet.svg",
      "codepoint": 61869
    },
    "camera": {
      "source": "svg/camera.svg",
      "codepoint": 61824
    },
    "checkmark": {
      "source": "svg/checkmark.svg",
      "codepoint": 61825
    },
    "chevron-down": {
      "source": "svg/chevron-down.svg",
      "codepoint": 61826
    },
    "chevron-left": {
      "source": "svg/chevron-left.svg",
      "codepoint": 61827
    },
    "chevron-right": {
      "source": "svg/chevron-right.svg",
      "codepoint": 61828
    },
    "chevron-up": {
      "source": "svg/chevron-up.svg",
      "codepoint": 61829
    },
    "cross": {
      "source": "svg/cross.svg",
      "codepoint": 61830
    },
    "database": {
      "source": "svg/database.svg",
      "codepoint": 61831
    },
    "decision-path": {
      "source": "svg/decision-path.svg",
      "codepoint": 61832
    },
    "double-chevron-down": {
      "source": "svg/double-chevron-down.svg",
      "codepoint": 61833
    },
    "double-chevron-left": {
      "source": "svg/double-chevron-left.svg",
      "codepoint": 61834
    },
    "double-chevron-right": {
      "source": "svg/double-chevron-right.svg",
      "codepoint": 61835
    },
    "double-chevron-up": {
      "source": "svg/double-chevron-up.svg",
      "codepoint": 61836
    },
    "download": {
      "source": "svg/download.svg",
      "codepoint": 61837
    },
    "external": {
      "source": "svg/external.svg",
      "codepoint": 61839
    },
    "filter": {
      "source": "svg/filter.svg",
      "codepoint": 61870
    },
    "generate": {
      "source": "svg/generate.svg",
      "codepoint": 61841
    },
    "help": {
      "source": "svg/help.svg",
      "codepoint": 61842
    },
    "home": {
      "source": "svg/home.svg",
      "codepoint": 61843
    },
    "location": {
      "source": "svg/location.svg",
      "codepoint": 61844
    },
    "media-back": {
      "source": "svg/media-back.svg",
      "codepoint": 61873
    },
    "media-playback-pause": {
      "source": "svg/media-playback-pause.svg",
      "codepoint": 61874
    },
    "media-playback-start": {
      "source": "svg/media-playback-start.svg",
      "codepoint": 61875
    },
    "media-seek-backward": {
      "source": "svg/media-seek-backward.svg",
      "codepoint": 61876
    },
    "media-seek-forward": {
      "source": "svg/media-seek-forward.svg",
      "codepoint": 61877
    },
    "media-skip-back": {
      "source": "svg/media-skip-back.svg",
      "codepoint": 61878
    },
    "media-skip-backward": {
      "source": "svg/media-skip-backward.svg",
      "codepoint": 61879
    },
    "media-skip-forward": {
      "source": "svg/media-skip-forward.svg",
      "codepoint": 61880
    },
    "media-skip-next": {
      "source": "svg/media-skip-next.svg",
      "codepoint": 61881
    },
    "naturalis": {
      "source": "svg/naturalis.svg",
      "codepoint": 61845
    },
    "pinch": {
      "source": "svg/pinch.svg",
      "codepoint": 61871
    },
    "refresh": {
      "source": "svg/refresh.svg",
      "codepoint": 61848
    },
    "search": {
      "source": "svg/search.svg",
      "codepoint": 61850
    },
    "sort_1_9": {
      "source": "svg/sort_1_9.svg",
      "codepoint": 61851
    },
    "sort_9_1": {
      "source": "svg/sort_9_1.svg",
      "codepoint": 61852
    },
    "sort_a_z": {
      "source": "svg/sort_a_z.svg",
      "codepoint": 61853
    },
    "sort_little_much": {
      "source": "svg/sort_little_much.svg",
      "codepoint": 61854
    },
    "sort_much_little": {
      "source": "svg/sort_much_little.svg",
      "codepoint": 61855
    },
    "sort_sortable": {
      "source": "svg/sort_sortable.svg",
      "codepoint": 61856
    },
    "sort_z_a": {
      "source": "svg/sort_z_a.svg",
      "codepoint": 61857
    },
    "square_empty": {
      "source": "svg/square_empty.svg",
      "codepoint": 61858
    },
    "square_full": {
      "source": "svg/square_full.svg",
      "codepoint": 61859
    },
    "steps": {
      "source": "svg/steps.svg",
      "codepoint": 61872
    },
    "tree": {
      "source": "svg/tree.svg",
      "codepoint": 61862
    },
    "triangle-down": {
      "source": "svg/triangle-down.svg",
      "codepoint": 61863
    },
    "triangle-down-right": {
      "source": "svg/triangle-down-right.svg",
      "codepoint": 61864
    },
    "triangle-left": {
      "source": "svg/triangle-left.svg",
      "codepoint": 61865
    },
    "triangle-right": {
      "source": "svg/triangle-right.svg",
      "codepoint": 61866
    },
    "triangle-up": {
      "source": "svg/triangle-up.svg",
      "codepoint": 61867
    }
  },
  "options": {
    "input": {
      "vectors": "svg/",
      "templates": "svg/"
    },
    "output": {
      "fonts": "app2",
      "css": "app2",
      "preview": "app2"
    },
    "config": false,
    "templates": [
      "../_icons.scss",
      "preview"
    ],
    "font_name": "app2",
    "font_design_size": 16,
    "font_em": 512,
    "font_ascent": 448,
    "font_descent": 64,
    "css_selector": ".icon-{{glyph}}",
    "preprocessor_path": null,
    "autowidth": false,
    "no_hash": true,
    "debug": true,
    "force": true,
    "quiet": false
  },
  "templates": [
    "app2/_icons.scss",
    "app2/app2-preview.html"
  ]
}